Metadata-Version: 2.1
Name: aws-omics-tools
Version: 0.11.0
Summary: This package has been renamed to aws-healthomics-tools
License: Apache-2.0
Author: Amazon Web Services
Requires-Python: >=3.10,<4.0
Classifier: License :: OSI Approved :: Apache Software License
Classifier: Programming Language :: Python :: 3
Classifier: Programming Language :: Python :: 3.10
Classifier: Programming Language :: Python :: 3.11
Classifier: Programming Language :: Python :: 3.12
Requires-Dist: aws-healthomics-tools (>=0.11,<0.12)
